{"type": "FeatureCollection", "features": [{"type": "Feature", "geometry": {"type": "Point", "coordinates": [25.914856533190008, 48.266924801891335]}, "properties": {"vehicle_id": "vehicle_1", "timestamp": "2024-12-09T17:38:05:Z", "color": "#358D90", "frame_time": "17:38:05:676", "confidence": "0.8536", "delay": true}}, {"type": "Feature", "geometry": {"type": "Point", "coordinates": [25.914847676692453, 48.26692745139658]}, "properties": {"vehicle_id": "vehicle_1", "timestamp": "2024-12-09T17:38:05:Z", "color": "#358D90", "frame_time": "17:38:05:709", "confidence": "0.8282", "delay": true}}, {"type": "Feature", "geometry": {"type": "Point", "coordinates": [25.91483819216402, 48.26693028878322]}, "properties": {"vehicle_id": "vehicle_1", "timestamp": "2024-12-09T17:38:05:Z", "color": "#358D90", "frame_time": "17:38:05:742", "confidence": "0.8268", "delay": true}}, {"type": "Feature", "geometry": {"type": "Point", "coordinates": [25.91477973724669, 48.26694748537617]}, "properties": {"vehicle_id": "vehicle_1", "timestamp": "2024-12-09T17:38:05:Z", "color": "#358D90", "frame_time": "17:38:05:909", "confidence": "0.8325", "delay": true}}, {"type": "Feature", "geometry": {"type": "Point", "coordinates": [25.914770225549724, 48.26695033089036]}, "properties": {"vehicle_id": "vehicle_1", "timestamp": "2024-12-09T17:38:05:Z", "color": "#358D90", "frame_time": "17:38:05:943", "confidence": "0.8407", "delay": true}}, {"type": "Feature", "geometry": {"type": "Point", "coordinates": [25.914754391147586, 48.26695497378807]}, "properties": {"vehicle_id": "vehicle_1", "timestamp": "2024-12-09T17:38:05:Z", "color": "#358D90", "frame_time": "17:38:05:976", "confidence": "0.8213", "delay": true}}, {"type": "Feature", "geometry": {"type": "Point", "coordinates": [25.914745724753747, 48.26695756642173]}, "properties": {"vehicle_id": "vehicle_1", "timestamp": "2024-12-09T17:38:06:Z", "color": "#358D90", "frame_time": "17:38:06:011", "confidence": "0.8331", "delay": true}}, {"type": "Feature", "geometry": {"type": "Point", "coordinates": [25.914736319811908, 48.26696037999901]}, "properties": {"vehicle_id": "vehicle_1", "timestamp": "2024-12-09T17:38:06:Z", "color": "#358D90", "frame_time": "17:38:06:042", "confidence": "0.8339", "delay": true}}, {"type": "Feature", "geometry": {"type": "Point", "coordinates": [25.914719835657934, 48.26696521727568]}, "properties": {"vehicle_id": "vehicle_1", "timestamp": "2024-12-09T17:38:06:Z", "color": "#358D90", "frame_time": "17:38:06:076", "confidence": "0.8174", "delay": true}}, {"type": "Feature", "geometry": {"type": "Point", "coordinates": [25.914711136719475, 48.26696781964528]}, "properties": {"vehicle_id": "vehicle_1", "timestamp": "2024-12-09T17:38:06:Z", "color": "#358D90", "frame_time": "17:38:06:109", "confidence": "0.8258", "delay": true}}, {"type": "Feature", "geometry": {"type": "Point", "coordinates": [25.914702252995202, 48.26697047729529]}, "properties": {"vehicle_id": "vehicle_1", "timestamp": "2024-12-09T17:38:06:Z", "color": "#358D90", "frame_time": "17:38:06:143", "confidence": "0.8196", "delay": true}}, {"type": "Feature", "geometry": {"type": "Point", "coordinates": [25.914684901852446, 48.266976274781]}, "properties": {"vehicle_id": "vehicle_1", "timestamp": "2024-12-09T17:38:06:Z", "color": "#358D90", "frame_time": "17:38:06:178", "confidence": "0.8377", "delay": true}}, {"type": "Feature", "geometry": {"type": "Point", "coordinates": [25.9146763741957, 48.2669788259099]}, "properties": {"vehicle_id": "vehicle_1", "timestamp": "2024-12-09T17:38:06:Z", "color": "#358D90", "frame_time": "17:38:06:209", "confidence": "0.8210", "delay": true}}, {"type": "Feature", "geometry": {"type": "Point", "coordinates": [25.914667394226594, 48.2669815123523]}, "properties": {"vehicle_id": "vehicle_1", "timestamp": "2024-12-09T17:38:06:Z", "color": "#358D90", "frame_time": "17:38:06:242", "confidence": "0.8161", "delay": true}}, {"type": "Feature", "geometry": {"type": "Point", "coordinates": [25.914649249840476, 48.266986247983326]}, "properties": {"vehicle_id": "vehicle_1", "timestamp": "2024-12-09T17:38:06:Z", "color": "#358D90", "frame_time": "17:38:06:277", "confidence": "0.8229", "delay": true}}, {"type": "Feature", "geometry": {"type": "Point", "coordinates": [25.914639746234712, 48.26698909107646]}, "properties": {"vehicle_id": "vehicle_1", "timestamp": "2024-12-09T17:38:06:Z", "color": "#358D90", "frame_time": "17:38:06:309", "confidence": "0.8128", "delay": true}}, {"type": "Feature", "geometry": {"type": "Point", "coordinates": [25.914629889673613, 48.266992039759515]}, "properties": {"vehicle_id": "vehicle_1", "timestamp": "2024-12-09T17:38:06:Z", "color": "#358D90", "frame_time": "17:38:06:342", "confidence": "0.8398", "delay": true}}, {"type": "Feature", "geometry": {"type": "Point", "coordinates": [25.91461291773157, 48.26699742464311]}, "properties": {"vehicle_id": "vehicle_1", "timestamp": "2024-12-09T17:38:06:Z", "color": "#358D90", "frame_time": "17:38:06:376", "confidence": "0.8309", "delay": true}}, {"type": "Feature", "geometry": {"type": "Point", "coordinates": [25.91460432310213, 48.266999995807275]}, "properties": {"vehicle_id": "vehicle_1", "timestamp": "2024-12-09T17:38:06:Z", "color": "#358D90", "frame_time": "17:38:06:410", "confidence": "0.8503", "delay": true}}, {"type": "Feature", "geometry": {"type": "Point", "coordinates": [25.914596170321687, 48.26700243478816]}, "properties": {"vehicle_id": "vehicle_1", "timestamp": "2024-12-09T17:38:06:Z", "color": "#358D90", "frame_time": "17:38:06:444", "confidence": "0.8356", "delay": true}}, {"type": "Feature", "geometry": {"type": "Point", "coordinates": [25.91457665013276, 48.26700828284376]}, "properties": {"vehicle_id": "vehicle_1", "timestamp": "2024-12-09T17:38:06:Z", "color": "#358D90", "frame_time": "17:38:06:476", "confidence": "0.8267", "delay": true}}, {"type": "Feature", "geometry": {"type": "Point", "coordinates": [25.91456808041972, 48.2670108465538]}, "properties": {"vehicle_id": "vehicle_1", "timestamp": "2024-12-09T17:38:06:Z", "color": "#358D90", "frame_time": "17:38:06:510", "confidence": "0.8431", "delay": true}}, {"type": "Feature", "geometry": {"type": "Point", "coordinates": [25.914540803975623, 48.267018715805904]}, "properties": {"vehicle_id": "vehicle_1", "timestamp": "2024-12-09T17:38:06:Z", "color": "#358D90", "frame_time": "17:38:06:576", "confidence": "0.8372", "delay": true}}, {"type": "Feature", "geometry": {"type": "Point", "coordinates": [25.914533077968013, 48.267021027113415]}, "properties": {"vehicle_id": "vehicle_1", "timestamp": "2024-12-09T17:38:06:Z", "color": "#358D90", "frame_time": "17:38:06:610", "confidence": "0.8486", "delay": true}}, {"type": "Feature", "geometry": {"type": "Point", "coordinates": [25.91452516888423, 48.267023393189874]}, "properties": {"vehicle_id": "vehicle_1", "timestamp": "2024-12-09T17:38:06:Z", "color": "#358D90", "frame_time": "17:38:06:643", "confidence": "0.8422", "delay": true}}, {"type": "Feature", "geometry": {"type": "Point", "coordinates": [25.91450787110478, 48.26702827723036]}, "properties": {"vehicle_id": "vehicle_1", "timestamp": "2024-12-09T17:38:06:Z", "color": "#358D90", "frame_time": "17:38:06:677", "confidence": "0.8125", "delay": true}}, {"type": "Feature", "geometry": {"type": "Point", "coordinates": [25.91450121316158, 48.26703026901628]}, "properties": {"vehicle_id": "vehicle_1", "timestamp": "2024-12-09T17:38:06:Z", "color": "#358D90", "frame_time": "17:38:06:711", "confidence": "0.8130", "delay": true}}, {"type": "Feature", "geometry": {"type": "Point", "coordinates": [25.914497150335148, 48.26703148444878]}, "properties": {"vehicle_id": "vehicle_1", "timestamp": "2024-12-09T17:38:06:Z", "color": "#358D90", "frame_time": "17:38:06:743", "confidence": "0.8032", "delay": true}}, {"type": "Feature", "geometry": {"type": "Point", "coordinates": [25.914771319163123, 48.266949575218]}, "properties": {"vehicle_id": "vehicle_2", "timestamp": "2024-12-09T17:38:06:Z", "color": "#83BCA7", "frame_time": "17:38:06:777", "confidence": "0.8155", "delay": true}}, {"type": "Feature", "geometry": {"type": "Point", "coordinates": [25.914752214404096, 48.26695529058474]}, "properties": {"vehicle_id": "vehicle_2", "timestamp": "2024-12-09T17:38:06:Z", "color": "#83BCA7", "frame_time": "17:38:06:844", "confidence": "0.8150", "delay": true}}, {"type": "Feature", "geometry": {"type": "Point", "coordinates": [25.914680125911275, 48.26697637755678]}, "properties": {"vehicle_id": "vehicle_2", "timestamp": "2024-12-09T17:38:07:Z", "color": "#83BCA7", "frame_time": "17:38:07:012", "confidence": "0.8254", "delay": true}}, {"type": "Feature", "geometry": {"type": "Point", "coordinates": [25.914647029972528, 48.26698609028961]}, "properties": {"vehicle_id": "vehicle_2", "timestamp": "2024-12-09T17:38:07:Z", "color": "#83BCA7", "frame_time": "17:38:07:077", "confidence": "0.8444", "delay": true}}, {"type": "Feature", "geometry": {"type": "Point", "coordinates": [25.914502696957396, 48.26702926884714]}, "properties": {"vehicle_id": "vehicle_1", "timestamp": "2024-12-09T17:38:07:Z", "color": "#358D90", "frame_time": "17:38:07:110", "confidence": "0.8048", "delay": true}}, {"type": "Feature", "geometry": {"type": "Point", "coordinates": [25.914638864770332, 48.26698853298544]}, "properties": {"vehicle_id": "vehicle_2", "timestamp": "2024-12-09T17:38:07:Z", "color": "#83BCA7", "frame_time": "17:38:07:110", "confidence": "0.8012", "delay": false}}, {"type": "Feature", "geometry": {"type": "Point", "coordinates": [25.91462797500686, 48.26699179075898]}, "properties": {"vehicle_id": "vehicle_2", "timestamp": "2024-12-09T17:38:07:Z", "color": "#83BCA7", "frame_time": "17:38:07:144", "confidence": "0.8127", "delay": true}}, {"type": "Feature", "geometry": {"type": "Point", "coordinates": [25.914511174683803, 48.2670267326568]}, "properties": {"vehicle_id": "vehicle_1", "timestamp": "2024-12-09T17:38:07:Z", "color": "#358D90", "frame_time": "17:38:07:144", "confidence": "0.8025", "delay": false}}, {"type": "Feature", "geometry": {"type": "Point", "coordinates": [25.914605783287016, 48.26699824139271]}, "properties": {"vehicle_id": "vehicle_2", "timestamp": "2024-12-09T17:38:07:Z", "color": "#83BCA7", "frame_time": "17:38:07:178", "confidence": "0.8151", "delay": true}}, {"type": "Feature", "geometry": {"type": "Point", "coordinates": [25.91459558363667, 48.26700129271229]}, "properties": {"vehicle_id": "vehicle_2", "timestamp": "2024-12-09T17:38:07:Z", "color": "#83BCA7", "frame_time": "17:38:07:210", "confidence": "0.8216", "delay": true}}, {"type": "Feature", "geometry": {"type": "Point", "coordinates": [25.914587400782743, 48.267003740688594]}, "properties": {"vehicle_id": "vehicle_2", "timestamp": "2024-12-09T17:38:07:Z", "color": "#83BCA7", "frame_time": "17:38:07:245", "confidence": "0.8331", "delay": true}}, {"type": "Feature", "geometry": {"type": "Point", "coordinates": [25.914524048025758, 48.267022693250794]}, "properties": {"vehicle_id": "vehicle_1", "timestamp": "2024-12-09T17:38:07:Z", "color": "#358D90", "frame_time": "17:38:07:245", "confidence": "0.8287", "delay": false}}, {"type": "Feature", "geometry": {"type": "Point", "coordinates": [25.914517885175474, 48.26702434869828]}, "properties": {"vehicle_id": "vehicle_1", "timestamp": "2024-12-09T17:38:07:Z", "color": "#358D90", "frame_time": "17:38:07:277", "confidence": "0.8427", "delay": true}}, {"type": "Feature", "geometry": {"type": "Point", "coordinates": [25.914563887286338, 48.26701058674315]}, "properties": {"vehicle_id": "vehicle_2", "timestamp": "2024-12-09T17:38:07:Z", "color": "#83BCA7", "frame_time": "17:38:07:277", "confidence": "0.8305", "delay": false}}, {"type": "Feature", "geometry": {"type": "Point", "coordinates": [25.91455506870448, 48.267013224903124]}, "properties": {"vehicle_id": "vehicle_2", "timestamp": "2024-12-09T17:38:07:Z", "color": "#83BCA7", "frame_time": "17:38:07:310", "confidence": "0.8529", "delay": true}}, {"type": "Feature", "geometry": {"type": "Point", "coordinates": [25.914546259051434, 48.26701586039197]}, "properties": {"vehicle_id": "vehicle_2", "timestamp": "2024-12-09T17:38:07:Z", "color": "#83BCA7", "frame_time": "17:38:07:343", "confidence": "0.8208", "delay": true}}, {"type": "Feature", "geometry": {"type": "Point", "coordinates": [25.914536492953108, 48.267018782010226]}, "properties": {"vehicle_id": "vehicle_1", "timestamp": "2024-12-09T17:38:07:Z", "color": "#358D90", "frame_time": "17:38:07:343", "confidence": "0.8056", "delay": false}}, {"type": "Feature", "geometry": {"type": "Point", "coordinates": [25.914521774216613, 48.26702369787218]}, "properties": {"vehicle_id": "vehicle_2", "timestamp": "2024-12-09T17:38:07:Z", "color": "#83BCA7", "frame_time": "17:38:07:377", "confidence": "0.8613", "delay": true}}, {"type": "Feature", "geometry": {"type": "Point", "coordinates": [25.914529593922115, 48.267021358535494]}, "properties": {"vehicle_id": "vehicle_1", "timestamp": "2024-12-09T17:38:07:Z", "color": "#358D90", "frame_time": "17:38:07:377", "confidence": "0.8356", "delay": false}}, {"type": "Feature", "geometry": {"type": "Point", "coordinates": [25.914540208391895, 48.26701818311941]}, "properties": {"vehicle_id": "vehicle_1", "timestamp": "2024-12-09T17:38:07:Z", "color": "#358D90", "frame_time": "17:38:07:411", "confidence": "0.8352", "delay": true}}, {"type": "Feature", "geometry": {"type": "Point", "coordinates": [25.914512929095775, 48.26702634397129]}, "properties": {"vehicle_id": "vehicle_2", "timestamp": "2024-12-09T17:38:07:Z", "color": "#83BCA7", "frame_time": "17:38:07:411", "confidence": "0.8323", "delay": false}}, {"type": "Feature", "geometry": {"type": "Point", "coordinates": [25.91450340789825, 48.267029192324934]}, "properties": {"vehicle_id": "vehicle_2", "timestamp": "2024-12-09T17:38:07:Z", "color": "#83BCA7", "frame_time": "17:38:07:444", "confidence": "0.8470", "delay": true}}, {"type": "Feature", "geometry": {"type": "Point", "coordinates": [25.914548343709797, 48.267015749364376]}, "properties": {"vehicle_id": "vehicle_1", "timestamp": "2024-12-09T17:38:07:Z", "color": "#358D90", "frame_time": "17:38:07:444", "confidence": "0.8271", "delay": false}}, {"type": "Feature", "geometry": {"type": "Point", "coordinates": [25.914479634432663, 48.267035816990706]}, "properties": {"vehicle_id": "vehicle_2", "timestamp": "2024-12-09T17:38:07:Z", "color": "#83BCA7", "frame_time": "17:38:07:477", "confidence": "0.8400", "delay": true}}, {"type": "Feature", "geometry": {"type": "Point", "coordinates": [25.91454281253787, 48.267016916681996]}, "properties": {"vehicle_id": "vehicle_1", "timestamp": "2024-12-09T17:38:07:Z", "color": "#358D90", "frame_time": "17:38:07:477", "confidence": "0.8092", "delay": false}}, {"type": "Feature", "geometry": {"type": "Point", "coordinates": [25.914470885755104, 48.267038434237705]}, "properties": {"vehicle_id": "vehicle_2", "timestamp": "2024-12-09T17:38:07:Z", "color": "#83BCA7", "frame_time": "17:38:07:511", "confidence": "0.8499", "delay": true}}, {"type": "Feature", "geometry": {"type": "Point", "coordinates": [25.91455268756756, 48.26701396247644]}, "properties": {"vehicle_id": "vehicle_1", "timestamp": "2024-12-09T17:38:07:Z", "color": "#358D90", "frame_time": "17:38:07:511", "confidence": "0.8260", "delay": false}}, {"type": "Feature", "geometry": {"type": "Point", "coordinates": [25.914462074684412, 48.26704107015019]}, "properties": {"vehicle_id": "vehicle_2", "timestamp": "2024-12-09T17:38:07:Z", "color": "#83BCA7", "frame_time": "17:38:07:544", "confidence": "0.8481", "delay": true}}, {"type": "Feature", "geometry": {"type": "Point", "coordinates": [25.914560182674798, 48.26701172024648]}, "properties": {"vehicle_id": "vehicle_1", "timestamp": "2024-12-09T17:38:07:Z", "color": "#358D90", "frame_time": "17:38:07:544", "confidence": "0.8022", "delay": false}}, {"type": "Feature", "geometry": {"type": "Point", "coordinates": [25.91443727137286, 48.26704870374442]}, "properties": {"vehicle_id": "vehicle_2", "timestamp": "2024-12-09T17:38:07:Z", "color": "#83BCA7", "frame_time": "17:38:07:578", "confidence": "0.8603", "delay": true}}, {"type": "Feature", "geometry": {"type": "Point", "coordinates": [25.914553554028945, 48.267013916726434]}, "properties": {"vehicle_id": "vehicle_1", "timestamp": "2024-12-09T17:38:07:Z", "color": "#358D90", "frame_time": "17:38:07:578", "confidence": "0.8438", "delay": false}}, {"type": "Feature", "geometry": {"type": "Point", "coordinates": [25.914562400281508, 48.26701127028924]}, "properties": {"vehicle_id": "vehicle_1", "timestamp": "2024-12-09T17:38:07:Z", "color": "#358D90", "frame_time": "17:38:07:611", "confidence": "0.8573", "delay": true}}, {"type": "Feature", "geometry": {"type": "Point", "coordinates": [25.914428589139177, 48.267051301113874]}, "properties": {"vehicle_id": "vehicle_2", "timestamp": "2024-12-09T17:38:07:Z", "color": "#83BCA7", "frame_time": "17:38:07:611", "confidence": "0.8469", "delay": false}}, {"type": "Feature", "geometry": {"type": "Point", "coordinates": [25.914417816209948, 48.267054523933986]}, "properties": {"vehicle_id": "vehicle_2", "timestamp": "2024-12-09T17:38:07:Z", "color": "#83BCA7", "frame_time": "17:38:07:644", "confidence": "0.8427", "delay": true}}, {"type": "Feature", "geometry": {"type": "Point", "coordinates": [25.914572472577074, 48.267008257070074]}, "properties": {"vehicle_id": "vehicle_1", "timestamp": "2024-12-09T17:38:07:Z", "color": "#358D90", "frame_time": "17:38:07:644", "confidence": "0.8307", "delay": false}}, {"type": "Feature", "geometry": {"type": "Point", "coordinates": [25.914395432781316, 48.267060732755795]}, "properties": {"vehicle_id": "vehicle_2", "timestamp": "2024-12-09T17:38:07:Z", "color": "#83BCA7", "frame_time": "17:38:07:677", "confidence": "0.8469", "delay": true}}, {"type": "Feature", "geometry": {"type": "Point", "coordinates": [25.914566994880214, 48.267009408391935]}, "properties": {"vehicle_id": "vehicle_1", "timestamp": "2024-12-09T17:38:07:Z", "color": "#358D90", "frame_time": "17:38:07:677", "confidence": "0.8127", "delay": false}}, {"type": "Feature", "geometry": {"type": "Point", "coordinates": [25.914386899372065, 48.267063285602866]}, "properties": {"vehicle_id": "vehicle_2", "timestamp": "2024-12-09T17:38:07:Z", "color": "#83BCA7", "frame_time": "17:38:07:711", "confidence": "0.8234", "delay": true}}, {"type": "Feature", "geometry": {"type": "Point", "coordinates": [25.914576528226767, 48.26700655640451]}, "properties": {"vehicle_id": "vehicle_1", "timestamp": "2024-12-09T17:38:07:Z", "color": "#358D90", "frame_time": "17:38:07:711", "confidence": "0.8130", "delay": false}}, {"type": "Feature", "geometry": {"type": "Point", "coordinates": [25.9145853917508, 48.2670039048006]}, "properties": {"vehicle_id": "vehicle_1", "timestamp": "2024-12-09T17:38:07:Z", "color": "#358D90", "frame_time": "17:38:07:744", "confidence": "0.8287", "delay": true}}, {"type": "Feature", "geometry": {"type": "Point", "coordinates": [25.91437782096444, 48.26706600149116]}, "properties": {"vehicle_id": "vehicle_2", "timestamp": "2024-12-09T17:38:07:Z", "color": "#83BCA7", "frame_time": "17:38:07:744", "confidence": "0.8194", "delay": false}}, {"type": "Feature", "geometry": {"type": "Point", "coordinates": [25.914577032284164, 48.26700731991597]}, "properties": {"vehicle_id": "vehicle_1", "timestamp": "2024-12-09T17:38:07:Z", "color": "#358D90", "frame_time": "17:38:07:777", "confidence": "0.8273", "delay": true}}, {"type": "Feature", "geometry": {"type": "Point", "coordinates": [25.914353222517953, 48.26707427463734]}, "properties": {"vehicle_id": "vehicle_2", "timestamp": "2024-12-09T17:38:07:Z", "color": "#83BCA7", "frame_time": "17:38:07:777", "confidence": "0.8240", "delay": false}}, {"type": "Feature", "geometry": {"type": "Point", "coordinates": [25.91434433659845, 48.267076932940746]}, "properties": {"vehicle_id": "vehicle_2", "timestamp": "2024-12-09T17:38:07:Z", "color": "#83BCA7", "frame_time": "17:38:07:811", "confidence": "0.8151", "delay": true}}, {"type": "Feature", "geometry": {"type": "Point", "coordinates": [25.914595348309888, 48.26700184051076]}, "properties": {"vehicle_id": "vehicle_1", "timestamp": "2024-12-09T17:38:07:Z", "color": "#358D90", "frame_time": "17:38:07:844", "confidence": "0.8385", "delay": true}}, {"type": "Feature", "geometry": {"type": "Point", "coordinates": [25.914336428580135, 48.267079298696146]}, "properties": {"vehicle_id": "vehicle_2", "timestamp": "2024-12-09T17:38:07:Z", "color": "#83BCA7", "frame_time": "17:38:07:844", "confidence": "0.8051", "delay": false}}, {"type": "Feature", "geometry": {"type": "Point", "coordinates": [25.91458924102043, 48.26700358186646]}, "properties": {"vehicle_id": "vehicle_1", "timestamp": "2024-12-09T17:38:07:Z", "color": "#358D90", "frame_time": "17:38:07:877", "confidence": "0.8398", "delay": true}}, {"type": "Feature", "geometry": {"type": "Point", "coordinates": [25.914598119170815, 48.267000925887515]}, "properties": {"vehicle_id": "vehicle_1", "timestamp": "2024-12-09T17:38:07:Z", "color": "#358D90", "frame_time": "17:38:07:912", "confidence": "0.8449", "delay": true}}, {"type": "Feature", "geometry": {"type": "Point", "coordinates": [25.91460834970774, 48.266997865329905]}, "properties": {"vehicle_id": "vehicle_1", "timestamp": "2024-12-09T17:38:07:Z", "color": "#358D90", "frame_time": "17:38:07:944", "confidence": "0.8204", "delay": true}}, {"type": "Feature", "geometry": {"type": "Point", "coordinates": [25.914600125206327, 48.26700024006984]}, "properties": {"vehicle_id": "vehicle_1", "timestamp": "2024-12-09T17:38:07:Z", "color": "#358D90", "frame_time": "17:38:07:978", "confidence": "0.8541", "delay": true}}, {"type": "Feature", "geometry": {"type": "Point", "coordinates": [25.91428837827427, 48.26709350197365]}, "properties": {"vehicle_id": "vehicle_2", "timestamp": "2024-12-09T17:38:07:Z", "color": "#83BCA7", "frame_time": "17:38:07:978", "confidence": "0.8317", "delay": false}}, {"type": "Feature", "geometry": {"type": "Point", "coordinates": [25.914294151154134, 48.26709177496462]}, "properties": {"vehicle_id": "vehicle_2", "timestamp": "2024-12-09T17:38:08:Z", "color": "#83BCA7", "frame_time": "17:38:08:010", "confidence": "0.8411", "delay": true}}, {"type": "Feature", "geometry": {"type": "Point", "coordinates": [25.914609777908783, 48.26699735237692]}, "properties": {"vehicle_id": "vehicle_1", "timestamp": "2024-12-09T17:38:08:Z", "color": "#358D90", "frame_time": "17:38:08:010", "confidence": "0.8086", "delay": false}}, {"type": "Feature", "geometry": {"type": "Point", "coordinates": [25.914300310226416, 48.26708993242266]}, "properties": {"vehicle_id": "vehicle_2", "timestamp": "2024-12-09T17:38:08:Z", "color": "#83BCA7", "frame_time": "17:38:08:046", "confidence": "0.8369", "delay": true}}, {"type": "Feature", "geometry": {"type": "Point", "coordinates": [25.914618567603785, 48.26699472286046]}, "properties": {"vehicle_id": "vehicle_1", "timestamp": "2024-12-09T17:38:08:Z", "color": "#358D90", "frame_time": "17:38:08:046", "confidence": "0.8290", "delay": false}}, {"type": "Feature", "geometry": {"type": "Point", "coordinates": [25.91457944003812, 48.2670064282243]}, "properties": {"vehicle_id": "vehicle_3", "timestamp": "2024-12-09T17:38:08:Z", "color": "#E7A4C0", "frame_time": "17:38:08:046", "confidence": "0.8027", "delay": false}}, {"type": "Feature", "geometry": {"type": "Point", "coordinates": [25.914290185165648, 48.26709257656474]}, "properties": {"vehicle_id": "vehicle_2", "timestamp": "2024-12-09T17:38:08:Z", "color": "#83BCA7", "frame_time": "17:38:08:078", "confidence": "0.8325", "delay": true}}, {"type": "Feature", "geometry": {"type": "Point", "coordinates": [25.914606059401788, 48.266998079949964]}, "properties": {"vehicle_id": "vehicle_1", "timestamp": "2024-12-09T17:38:08:Z", "color": "#358D90", "frame_time": "17:38:08:078", "confidence": "0.8298", "delay": false}}, {"type": "Feature", "geometry": {"type": "Point", "coordinates": [25.914298782024964, 48.267090004737064]}, "properties": {"vehicle_id": "vehicle_2", "timestamp": "2024-12-09T17:38:08:Z", "color": "#83BCA7", "frame_time": "17:38:08:111", "confidence": "0.8418", "delay": true}}, {"type": "Feature", "geometry": {"type": "Point", "coordinates": [25.914306640875072, 48.26708765369147]}, "properties": {"vehicle_id": "vehicle_2", "timestamp": "2024-12-09T17:38:08:Z", "color": "#83BCA7", "frame_time": "17:38:08:145", "confidence": "0.8562", "delay": true}}, {"type": "Feature", "geometry": {"type": "Point", "coordinates": [25.91429767922391, 48.26708994979009]}, "properties": {"vehicle_id": "vehicle_2", "timestamp": "2024-12-09T17:38:08:Z", "color": "#83BCA7", "frame_time": "17:38:08:178", "confidence": "0.8544", "delay": true}}, {"type": "Feature", "geometry": {"type": "Point", "coordinates": [25.914305256850515, 48.26708768287526]}, "properties": {"vehicle_id": "vehicle_2", "timestamp": "2024-12-09T17:38:08:Z", "color": "#83BCA7", "frame_time": "17:38:08:211", "confidence": "0.8480", "delay": true}}, {"type": "Feature", "geometry": {"type": "Point", "coordinates": [25.914314455970295, 48.26708493087622]}, "properties": {"vehicle_id": "vehicle_2", "timestamp": "2024-12-09T17:38:08:Z", "color": "#83BCA7", "frame_time": "17:38:08:245", "confidence": "0.8637", "delay": true}}, {"type": "Feature", "geometry": {"type": "Point", "coordinates": [25.91448676723603, 48.267033382418504]}, "properties": {"vehicle_id": "vehicle_3", "timestamp": "2024-12-09T17:38:08:Z", "color": "#E7A4C0", "frame_time": "17:38:08:245", "confidence": "0.8091", "delay": false}}, {"type": "Feature", "geometry": {"type": "Point", "coordinates": [25.914302895968834, 48.26708870513714]}, "properties": {"vehicle_id": "vehicle_2", "timestamp": "2024-12-09T17:38:08:Z", "color": "#83BCA7", "frame_time": "17:38:08:279", "confidence": "0.8542", "delay": true}}, {"type": "Feature", "geometry": {"type": "Point", "coordinates": [25.91431071704162, 48.267086365393475]}, "properties": {"vehicle_id": "vehicle_2", "timestamp": "2024-12-09T17:38:08:Z", "color": "#83BCA7", "frame_time": "17:38:08:311", "confidence": "0.8509", "delay": true}}, {"type": "Feature", "geometry": {"type": "Point", "coordinates": [25.914448636962398, 48.26704510541932]}, "properties": {"vehicle_id": "vehicle_3", "timestamp": "2024-12-09T17:38:08:Z", "color": "#E7A4C0", "frame_time": "17:38:08:311", "confidence": "0.8238", "delay": false}}, {"type": "Feature", "geometry": {"type": "Point", "coordinates": [25.914318869049072, 48.26708392664776]}, "properties": {"vehicle_id": "vehicle_2", "timestamp": "2024-12-09T17:38:08:Z", "color": "#83BCA7", "frame_time": "17:38:08:345", "confidence": "0.8373", "delay": true}}, {"type": "Feature", "geometry": {"type": "Point", "coordinates": [25.91443906148843, 48.267047970007745]}, "properties": {"vehicle_id": "vehicle_3", "timestamp": "2024-12-09T17:38:08:Z", "color": "#E7A4C0", "frame_time": "17:38:08:345", "confidence": "0.8030", "delay": false}}, {"type": "Feature", "geometry": {"type": "Point", "coordinates": [25.914310698379907, 48.267086285278]}, "properties": {"vehicle_id": "vehicle_2", "timestamp": "2024-12-09T17:38:08:Z", "color": "#83BCA7", "frame_time": "17:38:08:378", "confidence": "0.8417", "delay": true}}, {"type": "Feature", "geometry": {"type": "Point", "coordinates": [25.91441319396805, 48.26705562281184]}, "properties": {"vehicle_id": "vehicle_3", "timestamp": "2024-12-09T17:38:08:Z", "color": "#E7A4C0", "frame_time": "17:38:08:378", "confidence": "0.8107", "delay": false}}, {"type": "Feature", "geometry": {"type": "Point", "coordinates": [25.91431996580579, 48.26708351284518]}, "properties": {"vehicle_id": "vehicle_2", "timestamp": "2024-12-09T17:38:08:Z", "color": "#83BCA7", "frame_time": "17:38:08:412", "confidence": "0.8218", "delay": true}}, {"type": "Feature", "geometry": {"type": "Point", "coordinates": [25.914404300353564, 48.26705828341566]}, "properties": {"vehicle_id": "vehicle_3", "timestamp": "2024-12-09T17:38:08:Z", "color": "#E7A4C0", "frame_time": "17:38:08:412", "confidence": "0.8101", "delay": false}}, {"type": "Feature", "geometry": {"type": "Point", "coordinates": [25.91432882482308, 48.26708086259142]}, "properties": {"vehicle_id": "vehicle_2", "timestamp": "2024-12-09T17:38:08:Z", "color": "#83BCA7", "frame_time": "17:38:08:445", "confidence": "0.8411", "delay": true}}, {"type": "Feature", "geometry": {"type": "Point", "coordinates": [25.91439546851433, 48.26706092553886]}, "properties": {"vehicle_id": "vehicle_3", "timestamp": "2024-12-09T17:38:08:Z", "color": "#E7A4C0", "frame_time": "17:38:08:445", "confidence": "0.8345", "delay": false}}, {"type": "Feature", "geometry": {"type": "Point", "coordinates": [25.914318684605195, 48.267083212112944]}, "properties": {"vehicle_id": "vehicle_2", "timestamp": "2024-12-09T17:38:08:Z", "color": "#83BCA7", "frame_time": "17:38:08:478", "confidence": "0.8075", "delay": true}}, {"type": "Feature", "geometry": {"type": "Point", "coordinates": [25.91432677289239, 48.26708079243018]}, "properties": {"vehicle_id": "vehicle_2", "timestamp": "2024-12-09T17:38:08:Z", "color": "#83BCA7", "frame_time": "17:38:08:511", "confidence": "0.8096", "delay": true}}, {"type": "Feature", "geometry": {"type": "Point", "coordinates": [25.914357343124127, 48.267071647074545]}, "properties": {"vehicle_id": "vehicle_3", "timestamp": "2024-12-09T17:38:08:Z", "color": "#E7A4C0", "frame_time": "17:38:08:511", "confidence": "0.8017", "delay": false}}, {"type": "Feature", "geometry": {"type": "Point", "coordinates": [25.914347053153758, 48.26707472541033]}, "properties": {"vehicle_id": "vehicle_3", "timestamp": "2024-12-09T17:38:08:Z", "color": "#E7A4C0", "frame_time": "17:38:08:545", "confidence": "0.8408", "delay": true}}, {"type": "Feature", "geometry": {"type": "Point", "coordinates": [25.91433612616945, 48.26707799431449]}, "properties": {"vehicle_id": "vehicle_2", "timestamp": "2024-12-09T17:38:08:Z", "color": "#83BCA7", "frame_time": "17:38:08:545", "confidence": "0.8109", "delay": false}}, {"type": "Feature", "geometry": {"type": "Point", "coordinates": [25.914319868104624, 48.26708317404591]}, "properties": {"vehicle_id": "vehicle_3", "timestamp": "2024-12-09T17:38:08:Z", "color": "#E7A4C0", "frame_time": "17:38:08:578", "confidence": "0.8241", "delay": true}}, {"type": "Feature", "geometry": {"type": "Point", "coordinates": [25.914324746136554, 48.26708171473961]}, "properties": {"vehicle_id": "vehicle_2", "timestamp": "2024-12-09T17:38:08:Z", "color": "#83BCA7", "frame_time": "17:38:08:578", "confidence": "0.8186", "delay": false}}, {"type": "Feature", "geometry": {"type": "Point", "coordinates": [25.91431165606293, 48.267085630750636]}, "properties": {"vehicle_id": "vehicle_3", "timestamp": "2024-12-09T17:38:08:Z", "color": "#E7A4C0", "frame_time": "17:38:08:613", "confidence": "0.8356", "delay": true}}, {"type": "Feature", "geometry": {"type": "Point", "coordinates": [25.914335654623923, 48.267078451369365]}, "properties": {"vehicle_id": "vehicle_2", "timestamp": "2024-12-09T17:38:08:Z", "color": "#83BCA7", "frame_time": "17:38:08:613", "confidence": "0.8184", "delay": false}}, {"type": "Feature", "geometry": {"type": "Point", "coordinates": [25.914302112183805, 48.26708848588628]}, "properties": {"vehicle_id": "vehicle_3", "timestamp": "2024-12-09T17:38:08:Z", "color": "#E7A4C0", "frame_time": "17:38:08:645", "confidence": "0.8339", "delay": true}}, {"type": "Feature", "geometry": {"type": "Point", "coordinates": [25.914344447928816, 48.267075820774615]}, "properties": {"vehicle_id": "vehicle_2", "timestamp": "2024-12-09T17:38:08:Z", "color": "#83BCA7", "frame_time": "17:38:08:645", "confidence": "0.8057", "delay": false}}, {"type": "Feature", "geometry": {"type": "Point", "coordinates": [25.914335244793993, 48.26707818912043]}, "properties": {"vehicle_id": "vehicle_2", "timestamp": "2024-12-09T17:38:08:Z", "color": "#83BCA7", "frame_time": "17:38:08:678", "confidence": "0.8101", "delay": false}}, {"type": "Feature", "geometry": {"type": "Point", "coordinates": [25.914351586220633, 48.267073300438945]}, "properties": {"vehicle_id": "vehicle_2", "timestamp": "2024-12-09T17:38:08:Z", "color": "#83BCA7", "frame_time": "17:38:08:746", "confidence": "0.8107", "delay": true}}, {"type": "Feature", "geometry": {"type": "Point", "coordinates": [25.91422759758869, 48.26711111039827]}, "properties": {"vehicle_id": "vehicle_3", "timestamp": "2024-12-09T17:38:08:Z", "color": "#E7A4C0", "frame_time": "17:38:08:778", "confidence": "0.8329", "delay": true}}, {"type": "Feature", "geometry": {"type": "Point", "coordinates": [25.914340231440104, 48.267077414995704]}, "properties": {"vehicle_id": "vehicle_2", "timestamp": "2024-12-09T17:38:08:Z", "color": "#83BCA7", "frame_time": "17:38:08:778", "confidence": "0.8201", "delay": false}}, {"type": "Feature", "geometry": {"type": "Point", "coordinates": [25.914349043047707, 48.267074778926165]}, "properties": {"vehicle_id": "vehicle_2", "timestamp": "2024-12-09T17:38:08:Z", "color": "#83BCA7", "frame_time": "17:38:08:812", "confidence": "0.8277", "delay": true}}, {"type": "Feature", "geometry": {"type": "Point", "coordinates": [25.9142187030704, 48.26711377127127]}, "properties": {"vehicle_id": "vehicle_3", "timestamp": "2024-12-09T17:38:08:Z", "color": "#E7A4C0", "frame_time": "17:38:08:812", "confidence": "0.8249", "delay": false}}, {"type": "Feature", "geometry": {"type": "Point", "coordinates": [25.914210524705858, 48.267116217900615]}, "properties": {"vehicle_id": "vehicle_3", "timestamp": "2024-12-09T17:38:08:Z", "color": "#E7A4C0", "frame_time": "17:38:08:846", "confidence": "0.8311", "delay": true}}, {"type": "Feature", "geometry": {"type": "Point", "coordinates": [25.914180303371776, 48.26712527570496]}, "properties": {"vehicle_id": "vehicle_3", "timestamp": "2024-12-09T17:38:08:Z", "color": "#E7A4C0", "frame_time": "17:38:08:879", "confidence": "0.8272", "delay": true}}, {"type": "Feature", "geometry": {"type": "Point", "coordinates": [25.914170725976927, 48.26712814086613]}, "properties": {"vehicle_id": "vehicle_3", "timestamp": "2024-12-09T17:38:08:Z", "color": "#E7A4C0", "frame_time": "17:38:08:912", "confidence": "0.8452", "delay": true}}, {"type": "Feature", "geometry": {"type": "Point", "coordinates": [25.91435624719399, 48.26707264057664]}, "properties": {"vehicle_id": "vehicle_2", "timestamp": "2024-12-09T17:38:08:Z", "color": "#83BCA7", "frame_time": "17:38:08:912", "confidence": "0.8118", "delay": false}}, {"type": "Feature", "geometry": {"type": "Point", "coordinates": [25.914363783944193, 48.26707038589211]}, "properties": {"vehicle_id": "vehicle_2", "timestamp": "2024-12-09T17:38:08:Z", "color": "#83BCA7", "frame_time": "17:38:08:945", "confidence": "0.8141", "delay": true}}, {"type": "Feature", "geometry": {"type": "Point", "coordinates": [25.914163233999105, 48.26713038215661]}, "properties": {"vehicle_id": "vehicle_3", "timestamp": "2024-12-09T17:38:08:Z", "color": "#E7A4C0", "frame_time": "17:38:08:945", "confidence": "0.8045", "delay": false}}, {"type": "Feature", "geometry": {"type": "Point", "coordinates": [25.914354707633045, 48.26707211798336]}, "properties": {"vehicle_id": "vehicle_2", "timestamp": "2024-12-09T17:38:08:Z", "color": "#83BCA7", "frame_time": "17:38:08:982", "confidence": "0.8242", "delay": true}}, {"type": "Feature", "geometry": {"type": "Point", "coordinates": [25.914135016740715, 48.26713784042267]}, "properties": {"vehicle_id": "vehicle_3", "timestamp": "2024-12-09T17:38:08:Z", "color": "#E7A4C0", "frame_time": "17:38:08:982", "confidence": "0.8145", "delay": false}}, {"type": "Feature", "geometry": {"type": "Point", "coordinates": [25.914125439311007, 48.26714070559398]}, "properties": {"vehicle_id": "vehicle_3", "timestamp": "2024-12-09T17:38:09:Z", "color": "#E7A4C0", "frame_time": "17:38:09:013", "confidence": "0.8229", "delay": true}}, {"type": "Feature", "geometry": {"type": "Point", "coordinates": [25.914363533701863, 48.267069477588194]}, "properties": {"vehicle_id": "vehicle_2", "timestamp": "2024-12-09T17:38:09:Z", "color": "#83BCA7", "frame_time": "17:38:09:013", "confidence": "0.8190", "delay": false}}, {"type": "Feature", "geometry": {"type": "Point", "coordinates": [25.914116543327044, 48.26714336690488]}, "properties": {"vehicle_id": "vehicle_3", "timestamp": "2024-12-09T17:38:09:Z", "color": "#E7A4C0", "frame_time": "17:38:09:045", "confidence": "0.8152", "delay": true}}, {"type": "Feature", "geometry": {"type": "Point", "coordinates": [25.91437236250469, 48.26706683637511]}, "properties": {"vehicle_id": "vehicle_2", "timestamp": "2024-12-09T17:38:09:Z", "color": "#83BCA7", "frame_time": "17:38:09:045", "confidence": "0.8043", "delay": false}}, {"type": "Feature", "geometry": {"type": "Point", "coordinates": [25.914361186790668, 48.26707119652559]}, "properties": {"vehicle_id": "vehicle_2", "timestamp": "2024-12-09T17:38:09:Z", "color": "#83BCA7", "frame_time": "17:38:09:082", "confidence": "0.8298", "delay": true}}, {"type": "Feature", "geometry": {"type": "Point", "coordinates": [25.914087691240294, 48.267153015084645]}, "properties": {"vehicle_id": "vehicle_3", "timestamp": "2024-12-09T17:38:09:Z", "color": "#E7A4C0", "frame_time": "17:38:09:082", "confidence": "0.8246", "delay": false}}, {"type": "Feature", "geometry": {"type": "Point", "coordinates": [25.914076827567616, 48.267156265046275]}, "properties": {"vehicle_id": "vehicle_3", "timestamp": "2024-12-09T17:38:09:Z", "color": "#E7A4C0", "frame_time": "17:38:09:112", "confidence": "0.8109", "delay": true}}, {"type": "Feature", "geometry": {"type": "Point", "coordinates": [25.91437761974474, 48.26706628046527]}, "properties": {"vehicle_id": "vehicle_2", "timestamp": "2024-12-09T17:38:09:Z", "color": "#83BCA7", "frame_time": "17:38:09:145", "confidence": "0.8189", "delay": true}}, {"type": "Feature", "geometry": {"type": "Point", "coordinates": [25.9140679588858, 48.26715891818914]}, "properties": {"vehicle_id": "vehicle_3", "timestamp": "2024-12-09T17:38:09:Z", "color": "#E7A4C0", "frame_time": "17:38:09:145", "confidence": "0.8012", "delay": false}}, {"type": "Feature", "geometry": {"type": "Point", "coordinates": [25.914367186794987, 48.267069418410905]}, "properties": {"vehicle_id": "vehicle_2", "timestamp": "2024-12-09T17:38:09:Z", "color": "#83BCA7", "frame_time": "17:38:09:179", "confidence": "0.8261", "delay": true}}, {"type": "Feature", "geometry": {"type": "Point", "coordinates": [25.914374600869465, 48.26706720042667]}, "properties": {"vehicle_id": "vehicle_2", "timestamp": "2024-12-09T17:38:09:Z", "color": "#83BCA7", "frame_time": "17:38:09:212", "confidence": "0.8412", "delay": true}}, {"type": "Feature", "geometry": {"type": "Point", "coordinates": [25.914384176903642, 48.267064335673574]}, "properties": {"vehicle_id": "vehicle_2", "timestamp": "2024-12-09T17:38:09:Z", "color": "#83BCA7", "frame_time": "17:38:09:245", "confidence": "0.8219", "delay": true}}, {"type": "Feature", "geometry": {"type": "Point", "coordinates": [25.914367189088402, 48.26706913540614]}, "properties": {"vehicle_id": "vehicle_2", "timestamp": "2024-12-09T17:38:09:Z", "color": "#83BCA7", "frame_time": "17:38:09:279", "confidence": "0.8331", "delay": true}}, {"type": "Feature", "geometry": {"type": "Point", "coordinates": [25.914376494484927, 48.26706635161695]}, "properties": {"vehicle_id": "vehicle_2", "timestamp": "2024-12-09T17:38:09:Z", "color": "#83BCA7", "frame_time": "17:38:09:346", "confidence": "0.8005", "delay": true}}, {"type": "Feature", "geometry": {"type": "Point", "coordinates": [25.91407064708462, 48.26715756616259]}, "properties": {"vehicle_id": "vehicle_3", "timestamp": "2024-12-09T17:38:09:Z", "color": "#E7A4C0", "frame_time": "17:38:09:446", "confidence": "0.8119", "delay": true}}, {"type": "Feature", "geometry": {"type": "Point", "coordinates": [25.91407892850497, 48.267155540891096]}, "properties": {"vehicle_id": "vehicle_3", "timestamp": "2024-12-09T17:38:09:Z", "color": "#E7A4C0", "frame_time": "17:38:09:713", "confidence": "0.8220", "delay": true}}, {"type": "Feature", "geometry": {"type": "Point", "coordinates": [25.914087821939408, 48.2671528803452]}, "properties": {"vehicle_id": "vehicle_3", "timestamp": "2024-12-09T17:38:09:Z", "color": "#E7A4C0", "frame_time": "17:38:09:746", "confidence": "0.8254", "delay": true}}, {"type": "Feature", "geometry": {"type": "Point", "coordinates": [25.914070626446037, 48.26715784472613]}, "properties": {"vehicle_id": "vehicle_1", "timestamp": "2024-12-09T17:38:09:Z", "color": "#358D90", "frame_time": "17:38:09:780", "confidence": "0.8142", "delay": true}}, {"type": "Feature", "geometry": {"type": "Point", "coordinates": [25.914078812438927, 48.267155395817674]}, "properties": {"vehicle_id": "vehicle_1", "timestamp": "2024-12-09T17:38:09:Z", "color": "#358D90", "frame_time": "17:38:09:812", "confidence": "0.8229", "delay": true}}, {"type": "Feature", "geometry": {"type": "Point", "coordinates": [25.91407663097828, 48.26715646694294]}, "properties": {"vehicle_id": "vehicle_1", "timestamp": "2024-12-09T17:38:09:Z", "color": "#358D90", "frame_time": "17:38:09:882", "confidence": "0.8165", "delay": true}}, {"type": "Feature", "geometry": {"type": "Point", "coordinates": [25.914085481752995, 48.267153819159795]}, "properties": {"vehicle_id": "vehicle_1", "timestamp": "2024-12-09T17:38:09:Z", "color": "#358D90", "frame_time": "17:38:09:913", "confidence": "0.8123", "delay": true}}, {"type": "Feature", "geometry": {"type": "Point", "coordinates": [25.914094363883674, 48.26715116199624]}, "properties": {"vehicle_id": "vehicle_1", "timestamp": "2024-12-09T17:38:09:Z", "color": "#358D90", "frame_time": "17:38:09:946", "confidence": "0.8166", "delay": true}}, {"type": "Feature", "geometry": {"type": "Point", "coordinates": [25.914081561154283, 48.26715470972172]}, "properties": {"vehicle_id": "vehicle_1", "timestamp": "2024-12-09T17:38:09:Z", "color": "#358D90", "frame_time": "17:38:09:980", "confidence": "0.8001", "delay": true}}, {"type": "Feature", "geometry": {"type": "Point", "coordinates": [25.914091127199352, 48.26715184795981]}, "properties": {"vehicle_id": "vehicle_1", "timestamp": "2024-12-09T17:38:10:Z", "color": "#358D90", "frame_time": "17:38:10:012", "confidence": "0.8004", "delay": true}}, {"type": "Feature", "geometry": {"type": "Point", "coordinates": [25.914099330175272, 48.26714939397136]}, "properties": {"vehicle_id": "vehicle_1", "timestamp": "2024-12-09T17:38:10:Z", "color": "#358D90", "frame_time": "17:38:10:046", "confidence": "0.8218", "delay": true}}, {"type": "Feature", "geometry": {"type": "Point", "coordinates": [25.91408587341617, 48.2671535390413]}, "properties": {"vehicle_id": "vehicle_3", "timestamp": "2024-12-09T17:38:10:Z", "color": "#E7A4C0", "frame_time": "17:38:10:079", "confidence": "0.8188", "delay": true}}, {"type": "Feature", "geometry": {"type": "Point", "coordinates": [25.914095420708986, 48.267150682889664]}, "properties": {"vehicle_id": "vehicle_3", "timestamp": "2024-12-09T17:38:10:Z", "color": "#E7A4C0", "frame_time": "17:38:10:113", "confidence": "0.8134", "delay": true}}, {"type": "Feature", "geometry": {"type": "Point", "coordinates": [25.914103623368586, 48.26714822899618]}, "properties": {"vehicle_id": "vehicle_3", "timestamp": "2024-12-09T17:38:10:Z", "color": "#E7A4C0", "frame_time": "17:38:10:148", "confidence": "0.8246", "delay": true}}, {"type": "Feature", "geometry": {"type": "Point", "coordinates": [25.914089801017802, 48.2671527825956]}, "properties": {"vehicle_id": "vehicle_1", "timestamp": "2024-12-09T17:38:10:Z", "color": "#358D90", "frame_time": "17:38:10:180", "confidence": "0.8042", "delay": true}}, {"type": "Feature", "geometry": {"type": "Point", "coordinates": [25.91410003010192, 48.26714972248088]}, "properties": {"vehicle_id": "vehicle_3", "timestamp": "2024-12-09T17:38:10:Z", "color": "#E7A4C0", "frame_time": "17:38:10:213", "confidence": "0.8143", "delay": true}}, {"type": "Feature", "geometry": {"type": "Point", "coordinates": [25.914108232472202, 48.267147268674286]}, "properties": {"vehicle_id": "vehicle_1", "timestamp": "2024-12-09T17:38:10:Z", "color": "#358D90", "frame_time": "17:38:10:246", "confidence": "0.8216", "delay": true}}, {"type": "Feature", "geometry": {"type": "Point", "coordinates": [25.91409311129407, 48.2671516125136]}, "properties": {"vehicle_id": "vehicle_3", "timestamp": "2024-12-09T17:38:10:Z", "color": "#E7A4C0", "frame_time": "17:38:10:282", "confidence": "0.8228", "delay": true}}, {"type": "Feature", "geometry": {"type": "Point", "coordinates": [25.914103339562892, 48.2671485526432]}, "properties": {"vehicle_id": "vehicle_1", "timestamp": "2024-12-09T17:38:10:Z", "color": "#358D90", "frame_time": "17:38:10:315", "confidence": "0.8257", "delay": true}}, {"type": "Feature", "geometry": {"type": "Point", "coordinates": [25.914112224492424, 48.267145894643754]}, "properties": {"vehicle_id": "vehicle_3", "timestamp": "2024-12-09T17:38:10:Z", "color": "#E7A4C0", "frame_time": "17:38:10:348", "confidence": "0.8152", "delay": true}}, {"type": "Feature", "geometry": {"type": "Point", "coordinates": [25.91410008215008, 48.26714924481415]}, "properties": {"vehicle_id": "vehicle_3", "timestamp": "2024-12-09T17:38:10:Z", "color": "#E7A4C0", "frame_time": "17:38:10:384", "confidence": "0.8379", "delay": true}}, {"type": "Feature", "geometry": {"type": "Point", "coordinates": [25.914108946570927, 48.267146592950354]}, "properties": {"vehicle_id": "vehicle_3", "timestamp": "2024-12-09T17:38:10:Z", "color": "#E7A4C0", "frame_time": "17:38:10:415", "confidence": "0.8279", "delay": true}}, {"type": "Feature", "geometry": {"type": "Point", "coordinates": [25.91411711065717, 48.267144150597375]}, "properties": {"vehicle_id": "vehicle_3", "timestamp": "2024-12-09T17:38:10:Z", "color": "#E7A4C0", "frame_time": "17:38:10:447", "confidence": "0.8139", "delay": true}}, {"type": "Feature", "geometry": {"type": "Point", "coordinates": [25.91410368736769, 48.26714828566051]}, "properties": {"vehicle_id": "vehicle_3", "timestamp": "2024-12-09T17:38:10:Z", "color": "#E7A4C0", "frame_time": "17:38:10:483", "confidence": "0.8168", "delay": true}}, {"type": "Feature", "geometry": {"type": "Point", "coordinates": [25.914110526437447, 48.2671462396973]}, "properties": {"vehicle_id": "vehicle_3", "timestamp": "2024-12-09T17:38:10:Z", "color": "#E7A4C0", "frame_time": "17:38:10:513", "confidence": "0.8159", "delay": true}}, {"type": "Feature", "geometry": {"type": "Point", "coordinates": [25.914114617457493, 48.267145015835446]}, "properties": {"vehicle_id": "vehicle_1", "timestamp": "2024-12-09T17:38:10:Z", "color": "#358D90", "frame_time": "17:38:10:547", "confidence": "0.8032", "delay": true}}, {"type": "Feature", "geometry": {"type": "Point", "coordinates": [25.91381830777039, 48.26723319433415]}, "properties": {"vehicle_id": "vehicle_2", "timestamp": "2024-12-09T17:38:11:Z", "color": "#83BCA7", "frame_time": "17:38:11:681", "confidence": "0.8570", "delay": true}}, {"type": "Feature", "geometry": {"type": "Point", "coordinates": [25.913815623947897, 48.26723399722013]}, "properties": {"vehicle_id": "vehicle_2", "timestamp": "2024-12-09T17:38:11:Z", "color": "#83BCA7", "frame_time": "17:38:11:715", "confidence": "0.8413", "delay": true}}, {"type": "Feature", "geometry": {"type": "Point", "coordinates": [25.91381227017357, 48.26723500052731]}, "properties": {"vehicle_id": "vehicle_2", "timestamp": "2024-12-09T17:38:11:Z", "color": "#83BCA7", "frame_time": "17:38:11:750", "confidence": "0.8453", "delay": true}}, {"type": "Feature", "geometry": {"type": "Point", "coordinates": [25.913783577899455, 48.26724380595717]}, "properties": {"vehicle_id": "vehicle_2", "timestamp": "2024-12-09T17:38:11:Z", "color": "#83BCA7", "frame_time": "17:38:11:783", "confidence": "0.8388", "delay": true}}, {"type": "Feature", "geometry": {"type": "Point", "coordinates": [25.913782363140303, 48.267244169361575]}, "properties": {"vehicle_id": "vehicle_2", "timestamp": "2024-12-09T17:38:11:Z", "color": "#83BCA7", "frame_time": "17:38:11:815", "confidence": "0.8506", "delay": true}}, {"type": "Feature", "geometry": {"type": "Point", "coordinates": [25.913778343516004, 48.267245371862664]}, "properties": {"vehicle_id": "vehicle_2", "timestamp": "2024-12-09T17:38:11:Z", "color": "#83BCA7", "frame_time": "17:38:11:848", "confidence": "0.8382", "delay": true}}, {"type": "Feature", "geometry": {"type": "Point", "coordinates": [25.913753127448214, 48.26725273567189]}, "properties": {"vehicle_id": "vehicle_2", "timestamp": "2024-12-09T17:38:11:Z", "color": "#83BCA7", "frame_time": "17:38:11:884", "confidence": "0.8326", "delay": true}}, {"type": "Feature", "geometry": {"type": "Point", "coordinates": [25.91375045023901, 48.26725353657921]}, "properties": {"vehicle_id": "vehicle_5", "timestamp": "2024-12-09T17:38:11:Z", "color": "#3F3ABE", "frame_time": "17:38:11:915", "confidence": "0.8350", "delay": true}}, {"type": "Feature", "geometry": {"type": "Point", "coordinates": [25.913747104932025, 48.267254537353026]}, "properties": {"vehicle_id": "vehicle_5", "timestamp": "2024-12-09T17:38:11:Z", "color": "#3F3ABE", "frame_time": "17:38:11:948", "confidence": "0.8249", "delay": true}}, {"type": "Feature", "geometry": {"type": "Point", "coordinates": [25.913688673058825, 48.26727165815187]}, "properties": {"vehicle_id": "vehicle_5", "timestamp": "2024-12-09T17:38:12:Z", "color": "#3F3ABE", "frame_time": "17:38:12:086", "confidence": "0.8314", "delay": true}}, {"type": "Feature", "geometry": {"type": "Point", "coordinates": [25.913686671245824, 48.26727225700916]}, "properties": {"vehicle_id": "vehicle_5", "timestamp": "2024-12-09T17:38:12:Z", "color": "#3F3ABE", "frame_time": "17:38:12:114", "confidence": "0.8305", "delay": true}}, {"type": "Feature", "geometry": {"type": "Point", "coordinates": [25.91368214657042, 48.26727361059956]}, "properties": {"vehicle_id": "vehicle_5", "timestamp": "2024-12-09T17:38:12:Z", "color": "#3F3ABE", "frame_time": "17:38:12:149", "confidence": "0.8307", "delay": true}}, {"type": "Feature", "geometry": {"type": "Point", "coordinates": [25.913655808309983, 48.26728101096248]}, "properties": {"vehicle_id": "vehicle_5", "timestamp": "2024-12-09T17:38:12:Z", "color": "#3F3ABE", "frame_time": "17:38:12:184", "confidence": "0.8440", "delay": true}}, {"type": "Feature", "geometry": {"type": "Point", "coordinates": [25.913651960156123, 48.267282162166254]}, "properties": {"vehicle_id": "vehicle_5", "timestamp": "2024-12-09T17:38:12:Z", "color": "#3F3ABE", "frame_time": "17:38:12:216", "confidence": "0.8411", "delay": true}}, {"type": "Feature", "geometry": {"type": "Point", "coordinates": [25.913648633703794, 48.26728315729914]}, "properties": {"vehicle_id": "vehicle_5", "timestamp": "2024-12-09T17:38:12:Z", "color": "#3F3ABE", "frame_time": "17:38:12:249", "confidence": "0.8360", "delay": true}}, {"type": "Feature", "geometry": {"type": "Point", "coordinates": [25.913621971236186, 48.2672919538097]}, "properties": {"vehicle_id": "vehicle_5", "timestamp": "2024-12-09T17:38:12:Z", "color": "#3F3ABE", "frame_time": "17:38:12:282", "confidence": "0.8007", "delay": true}}, {"type": "Feature", "geometry": {"type": "Point", "coordinates": [25.91361946672884, 48.26729270305154]}, "properties": {"vehicle_id": "vehicle_5", "timestamp": "2024-12-09T17:38:12:Z", "color": "#3F3ABE", "frame_time": "17:38:12:316", "confidence": "0.8148", "delay": true}}, {"type": "Feature", "geometry": {"type": "Point", "coordinates": [25.913617474788946, 48.267293298955046]}, "properties": {"vehicle_id": "vehicle_5", "timestamp": "2024-12-09T17:38:12:Z", "color": "#3F3ABE", "frame_time": "17:38:12:349", "confidence": "0.8131", "delay": true}}, {"type": "Feature", "geometry": {"type": "Point", "coordinates": [25.913254034187602, 48.26740235425796]}, "properties": {"vehicle_id": "vehicle_5", "timestamp": "2024-12-09T17:38:13:Z", "color": "#3F3ABE", "frame_time": "17:38:13:384", "confidence": "0.8014", "delay": true}}, {"type": "Feature", "geometry": {"type": "Point", "coordinates": [25.913251874824084, 48.26740299122135]}, "properties": {"vehicle_id": "vehicle_5", "timestamp": "2024-12-09T17:38:13:Z", "color": "#3F3ABE", "frame_time": "17:38:13:417", "confidence": "0.8013", "delay": true}}, {"type": "Feature", "geometry": {"type": "Point", "coordinates": [25.91324804379455, 48.26740412128843]}, "properties": {"vehicle_id": "vehicle_5", "timestamp": "2024-12-09T17:38:13:Z", "color": "#3F3ABE", "frame_time": "17:38:13:450", "confidence": "0.8113", "delay": true}}, {"type": "Feature", "geometry": {"type": "Point", "coordinates": [25.913208431407305, 48.267415806046735]}, "properties": {"vehicle_id": "vehicle_2", "timestamp": "2024-12-09T17:38:13:Z", "color": "#83BCA7", "frame_time": "17:38:13:450", "confidence": "0.8013", "delay": false}}, {"type": "Feature", "geometry": {"type": "Point", "coordinates": [25.913220470400795, 48.26741415980576]}, "properties": {"vehicle_id": "vehicle_5", "timestamp": "2024-12-09T17:38:13:Z", "color": "#3F3ABE", "frame_time": "17:38:13:485", "confidence": "0.8015", "delay": true}}, {"type": "Feature", "geometry": {"type": "Point", "coordinates": [25.913217275428995, 48.267415062556054]}, "properties": {"vehicle_id": "vehicle_5", "timestamp": "2024-12-09T17:38:13:Z", "color": "#3F3ABE", "frame_time": "17:38:13:517", "confidence": "0.8099", "delay": true}}, {"type": "Feature", "geometry": {"type": "Point", "coordinates": [25.913214352751528, 48.267415888368646]}, "properties": {"vehicle_id": "vehicle_5", "timestamp": "2024-12-09T17:38:13:Z", "color": "#3F3ABE", "frame_time": "17:38:13:549", "confidence": "0.8141", "delay": true}}, {"type": "Feature", "geometry": {"type": "Point", "coordinates": [25.913081962738406, 48.267454794924504]}, "properties": {"vehicle_id": "vehicle_5", "timestamp": "2024-12-09T17:38:13:Z", "color": "#3F3ABE", "frame_time": "17:38:13:884", "confidence": "0.8220", "delay": true}}, {"type": "Feature", "geometry": {"type": "Point", "coordinates": [25.913078922537427, 48.26745559617253]}, "properties": {"vehicle_id": "vehicle_5", "timestamp": "2024-12-09T17:38:13:Z", "color": "#3F3ABE", "frame_time": "17:38:13:917", "confidence": "0.8320", "delay": true}}, {"type": "Feature", "geometry": {"type": "Point", "coordinates": [25.913076505021305, 48.26745623331134]}, "properties": {"vehicle_id": "vehicle_5", "timestamp": "2024-12-09T17:38:13:Z", "color": "#3F3ABE", "frame_time": "17:38:13:950", "confidence": "0.8370", "delay": true}}, {"type": "Feature", "geometry": {"type": "Point", "coordinates": [25.913047565727737, 48.26746408920735]}, "properties": {"vehicle_id": "vehicle_5", "timestamp": "2024-12-09T17:38:13:Z", "color": "#3F3ABE", "frame_time": "17:38:13:983", "confidence": "0.8269", "delay": true}}, {"type": "Feature", "geometry": {"type": "Point", "coordinates": [25.91304423989152, 48.26746497020741]}, "properties": {"vehicle_id": "vehicle_5", "timestamp": "2024-12-09T17:38:14:Z", "color": "#3F3ABE", "frame_time": "17:38:14:019", "confidence": "0.8298", "delay": true}}, {"type": "Feature", "geometry": {"type": "Point", "coordinates": [25.913040338541514, 48.26746600365867]}, "properties": {"vehicle_id": "vehicle_5", "timestamp": "2024-12-09T17:38:14:Z", "color": "#3F3ABE", "frame_time": "17:38:14:051", "confidence": "0.8217", "delay": true}}, {"type": "Feature", "geometry": {"type": "Point", "coordinates": [25.913012124741915, 48.26747302325681]}, "properties": {"vehicle_id": "vehicle_5", "timestamp": "2024-12-09T17:38:14:Z", "color": "#3F3ABE", "frame_time": "17:38:14:086", "confidence": "0.8503", "delay": true}}, {"type": "Feature", "geometry": {"type": "Point", "coordinates": [25.913008647612777, 48.267473939657464]}, "properties": {"vehicle_id": "vehicle_5", "timestamp": "2024-12-09T17:38:14:Z", "color": "#3F3ABE", "frame_time": "17:38:14:118", "confidence": "0.8395", "delay": true}}, {"type": "Feature", "geometry": {"type": "Point", "coordinates": [25.91300473825447, 48.26747496997252]}, "properties": {"vehicle_id": "vehicle_5", "timestamp": "2024-12-09T17:38:14:Z", "color": "#3F3ABE", "frame_time": "17:38:14:118", "confidence": "0.8308", "delay": false}}, {"type": "Feature", "geometry": {"type": "Point", "coordinates": [25.91300618407572, 48.26747458892497]}, "properties": {"vehicle_id": "vehicle_2", "timestamp": "2024-12-09T17:38:14:Z", "color": "#83BCA7", "frame_time": "17:38:14:151", "confidence": "0.8335", "delay": true}}, {"type": "Feature", "geometry": {"type": "Point", "coordinates": [25.91297675326935, 48.26748260234801]}, "properties": {"vehicle_id": "vehicle_2", "timestamp": "2024-12-09T17:38:14:Z", "color": "#83BCA7", "frame_time": "17:38:14:184", "confidence": "0.8196", "delay": true}}, {"type": "Feature", "geometry": {"type": "Point", "coordinates": [25.913087048728407, 48.267453271500926]}, "properties": {"vehicle_id": "vehicle_3", "timestamp": "2024-12-09T17:38:14:Z", "color": "#E7A4C0", "frame_time": "17:38:14:717", "confidence": "0.8208", "delay": true}}, {"type": "Feature", "geometry": {"type": "Point", "coordinates": [25.91304396547897, 48.267464510265164]}, "properties": {"vehicle_id": "vehicle_3", "timestamp": "2024-12-09T17:38:14:Z", "color": "#E7A4C0", "frame_time": "17:38:14:819", "confidence": "0.8223", "delay": true}}, {"type": "Feature", "geometry": {"type": "Point", "coordinates": [25.913038200711547, 48.26746602957366]}, "properties": {"vehicle_id": "vehicle_3", "timestamp": "2024-12-09T17:38:14:Z", "color": "#E7A4C0", "frame_time": "17:38:14:852", "confidence": "0.8454", "delay": true}}, {"type": "Feature", "geometry": {"type": "Point", "coordinates": [25.912997178501826, 48.26747583510915]}, "properties": {"vehicle_id": "vehicle_3", "timestamp": "2024-12-09T17:38:14:Z", "color": "#E7A4C0", "frame_time": "17:38:14:951", "confidence": "0.8484", "delay": true}}, {"type": "Feature", "geometry": {"type": "Point", "coordinates": [25.912967392600216, 48.26748451358647]}, "properties": {"vehicle_id": "vehicle_3", "timestamp": "2024-12-09T17:38:14:Z", "color": "#E7A4C0", "frame_time": "17:38:14:986", "confidence": "0.8461", "delay": true}}, {"type": "Feature", "geometry": {"type": "Point", "coordinates": [25.912962417461216, 48.26748582478751]}, "properties": {"vehicle_id": "vehicle_3", "timestamp": "2024-12-09T17:38:15:Z", "color": "#E7A4C0", "frame_time": "17:38:15:018", "confidence": "0.8172", "delay": true}}, {"type": "Feature", "geometry": {"type": "Point", "coordinates": [25.91295748522208, 48.26748712468226]}, "properties": {"vehicle_id": "vehicle_3", "timestamp": "2024-12-09T17:38:15:Z", "color": "#E7A4C0", "frame_time": "17:38:15:052", "confidence": "0.8561", "delay": true}}, {"type": "Feature", "geometry": {"type": "Point", "coordinates": [25.91288688389868, 48.267505290641985]}, "properties": {"vehicle_id": "vehicle_3", "timestamp": "2024-12-09T17:38:15:Z", "color": "#E7A4C0", "frame_time": "17:38:15:186", "confidence": "0.8418", "delay": true}}, {"type": "Feature", "geometry": {"type": "Point", "coordinates": [25.912882068720926, 48.267506559684804]}, "properties": {"vehicle_id": "vehicle_3", "timestamp": "2024-12-09T17:38:15:Z", "color": "#E7A4C0", "frame_time": "17:38:15:221", "confidence": "0.8295", "delay": true}}, {"type": "Feature", "geometry": {"type": "Point", "coordinates": [25.91287656252842, 48.26750801084496]}, "properties": {"vehicle_id": "vehicle_3", "timestamp": "2024-12-09T17:38:15:Z", "color": "#E7A4C0", "frame_time": "17:38:15:253", "confidence": "0.8120", "delay": true}}]}